{"ami_id":"ami-0e3df83cd6630da18","control_plane_ips":["10.0.135.168"],"lb_target_group_arns":["arn:aws:elasticloadbalancing:eu-west-1:056341052778:targetgroup/sno-1-wwr7m-aint/e04f502df27cfe6a","arn:aws:elasticloadbalancing:eu-west-1:056341052778:targetgroup/sno-1-wwr7m-sint/7202bc44eb9e4a86","arn:aws:elasticloadbalancing:eu-west-1:056341052778:targetgroup/sno-1-wwr7m-aext/860f09cc5994b7bc"],"lb_target_group_arns_length":"3","master_sg_id":"sg-08711eedc5eb6b529","private_subnet_ids":["subnet-00cabfbf3c303d6a6","subnet-0e242fe56a35c7a12","subnet-066cf441395b8d82c"],"public_subnet_ids":["subnet-060314dc649dc0a23","subnet-0a589b1f897251cad","subnet-03d9895c4c42bce13"],"vpc_id":"vpc-0e1ca3462357ea0ad"}